[{"name":"partman","path":"C:\\Users\\phcre\\Documents\\JS\\partman\\client\\dist\\partman_linux_amd64_v1\\partman","goos":"linux","goarch":"amd64","goamd64":"v1","internal_type":4,"type":"Binary","extra":{"Binary":"partman","Ext":"","ID":"partman"}},{"name":"partman","path":"C:\\Users\\phcre\\Documents\\JS\\partman\\client\\dist\\partman_linux_386\\partman","goos":"linux","goarch":"386","internal_type":4,"type":"Binary","extra":{"Binary":"partman","Ext":"","ID":"partman"}},{"name":"partman","path":"C:\\Users\\phcre\\Documents\\JS\\partman\\client\\dist\\partman_linux_arm64\\partman","goos":"linux","goarch":"arm64","internal_type":4,"type":"Binary","extra":{"Binary":"partman","Ext":"","ID":"partman"}},{"name":"partman","path":"C:\\Users\\phcre\\Documents\\JS\\partman\\client\\dist\\partman_darwin_amd64_v1\\partman","goos":"darwin","goarch":"amd64","goamd64":"v1","internal_type":4,"type":"Binary","extra":{"Binary":"partman","Ext":"","ID":"partman"}},{"name":"partman","path":"C:\\Users\\phcre\\Documents\\JS\\partman\\client\\dist\\partman_darwin_arm64\\partman","goos":"darwin","goarch":"arm64","internal_type":4,"type":"Binary","extra":{"Binary":"partman","Ext":"","ID":"partman"}}]